fracted/__init__.py
fracted/fractals.py
fracted/tools.py
fracted/transformations.py
fracted/types.py
fracted-0.1.0.dist-info/licenses/LICENSE
fracted-0.1.0.dist-info/METADATA
fracted-0.1.0.dist-info/WHEEL
fracted-0.1.0.dist-info/top_level.txt
fracted-0.1.0.dist-info/RECORD
