Metadata-Version: 2.4
Name: fracted
Version: 0.1.0
Summary: A simple library for drawing IFS fractals and fractal-flames
Author-email: Lukáš Koma <koma.luky@gmail.com>
License-Expression: MIT
Project-URL: Homepage, https://github.com/Skrret/fracted
Project-URL: Issues, https://github.com/Skrret/fracted/issues
Classifier: Programming Language :: Python :: 3
Classifier: Operating System :: OS Independent
Requires-Python: >=3.11
License-File: LICENSE
Requires-Dist: numpy>=1.23.0
Dynamic: license-file
